Metadata-Version: 2.1
Name: mancalagaming
Version: 0.3
Summary: base mancala functions
Home-page: https://github.com/alecsey-m-sorokin
Author: Alecsey.M.Sorokin
Author-email: alecsey.m.sorokin@gmail.com
License: AMS
Platform: UNKNOWN
